cdk_dev_cloud_constructs/__init__.py
cdk_dev_cloud_constructs/py.typed
cdk_dev_cloud_constructs/_jsii/__init__.py
cdk_dev_cloud_constructs/_jsii/cdk-dev-cloud-constructs@0.0.26.jsii.tgz
cdk_dev_cloud_constructs-0.0.26.dist-info/LICENSE
cdk_dev_cloud_constructs-0.0.26.dist-info/METADATA
cdk_dev_cloud_constructs-0.0.26.dist-info/WHEEL
cdk_dev_cloud_constructs-0.0.26.dist-info/top_level.txt
cdk_dev_cloud_constructs-0.0.26.dist-info/RECORD
