Metadata-Version: 2.1
Name: cdk-dev-cloud-constructs
Version: 0.0.26
Summary: CDK Construct Library to create an open source developer platform at AWS
Home-page: https://github.com/cloudbauer/cdk-dev-cloud-constructs
Author: bitbauer<4582513+bitbauer@users.noreply.github.com>
License: MIT
Project-URL: Source, https://github.com/cloudbauer/cdk-dev-cloud-constructs
Classifier: Intended Audience :: Developers
Classifier: Operating System :: OS Independent
Classifier: Programming Language :: JavaScript
Classifier: Programming Language :: Python :: 3 :: Only
Classifier: Programming Language :: Python :: 3.9
Classifier: Programming Language :: Python :: 3.10
Classifier: Programming Language :: Python :: 3.11
Classifier: Typing :: Typed
Classifier: Development Status :: 4 - Beta
Classifier: License :: OSI Approved
Requires-Python: ~=3.9
License-File: LICENSE
Requires-Dist: aws-cdk-lib <3.0.0,>=2.173.4
Requires-Dist: cdk-nag <3.0.0,>=2.36.50
Requires-Dist: constructs <11.0.0,>=10.4.2
Requires-Dist: jsii <2.0.0,>=1.113.0
Requires-Dist: publication >=0.0.3
Requires-Dist: typeguard <4.3.0,>=2.13.3
